asciify.py
asciifyy-1.0.4.dist-info/licenses/LICENSE
asciifyy-1.0.4.dist-info/METADATA
asciifyy-1.0.4.dist-info/WHEEL
asciifyy-1.0.4.dist-info/entry_points.txt
asciifyy-1.0.4.dist-info/top_level.txt
asciifyy-1.0.4.dist-info/RECORD
