Metadata-Version: 2.4
Name: asciifyy
Version: 1.0.4
Summary: Convert images to ASCII art in the terminal with optional color.
Author-email: Mark Mysler <myslermark@gmail.com>
License: MIT
Project-URL: Homepage, https://github.com/markmysler/asciify
Requires-Python: >=3.7
License-File: LICENSE
Requires-Dist: pillow
Requires-Dist: colorama
Dynamic: license-file
